Metadata-Version: 1.0
Name: dental
Version: 0.0.1
Summary: The dental python library.
Home-page: UNKNOWN
Author: PeterPyPan
Author-email: UNKNOWN
License: UNKNOWN
Platform: UNKNOWN
